odoo/addons/shopinvader_schema_address/README.rst
odoo/addons/shopinvader_schema_address/__init__.py
odoo/addons/shopinvader_schema_address/__manifest__.py
odoo/addons/shopinvader_schema_address/schemas.py
odoo/addons/shopinvader_schema_address/i18n/shopinvader_schema_address.pot
odoo/addons/shopinvader_schema_address/readme/CONTRIBUTORS.rst
odoo/addons/shopinvader_schema_address/readme/DESCRIPTION.rst
odoo/addons/shopinvader_schema_address/readme/HISTORY.rst
odoo/addons/shopinvader_schema_address/readme/newsfragments/.gitignore
odoo/addons/shopinvader_schema_address/static/description/icon.png
odoo/addons/shopinvader_schema_address/static/description/index.html
odoo_addon_shopinvader_schema_address-16.0.1.3.2.dist-info/METADATA
odoo_addon_shopinvader_schema_address-16.0.1.3.2.dist-info/WHEEL
odoo_addon_shopinvader_schema_address-16.0.1.3.2.dist-info/top_level.txt
odoo_addon_shopinvader_schema_address-16.0.1.3.2.dist-info/RECORD
